pykew/__init__.py
pykew/__version__.py
pykew/core.py
pykew/ipni.py
pykew/ipni_terms.py
pykew/kpl.py
pykew/powo.py
pykew/powo_terms.py
pykew/test_ipni.py
pykew/test_powo.py
pykew/__pycache__/__init__.cpython-35.pyc
pykew/ipni/__init__.py
pykew/ipni/config.py
pykew/ipni/search_result.py
pykew/ipni/terms/__init__.py
pykew/ipni/terms/author.py
pykew/ipni/terms/name.py
pykew/ipni/terms/publication.py
pykew/terms/__init__.py
pykew/terms/author.py
pykew/terms/name.py
pykew/terms/publication.py
pykew-0.1.2.dist-info/METADATA
pykew-0.1.2.dist-info/RECORD
pykew-0.1.2.dist-info/WHEEL
pykew-0.1.2.dist-info/top_level.txt
