Metadata-Version: 2.1
Name: pykew
Version: 0.1.2
Summary: Python interface to Kew data
Home-page: https://github.com/RBGKew/pykew
Author: John Iacona
Author-email: j.iacona@kew.org
License: MIT
Platform: UNKNOWN
Classifier: License :: OSI Approved :: MIT License
Classifier: Programming Language :: Python
Classifier: Programming Language :: Python :: 3
Classifier: Programming Language :: Python :: 3.6
Classifier: Programming Language :: Python :: Implementation :: CPython
Classifier: Programming Language :: Python :: Implementation :: PyPy
Requires-Python: >=3.5.0
Requires-Dist: requests
